py_solar/__init__.py
py_solar/__main__.py
py_solar/constants.py
py_solar/particle.py
py_solar/presets.py
py_solar/system.py
py_solar/test.py
py_solar-0.1.0.dist-info/WHEEL
py_solar-0.1.0.dist-info/METADATA
py_solar-0.1.0.dist-info/RECORD
